jaraco/vcs/__init__.py
jaraco/vcs/base.py
jaraco/vcs/cmd.py
jaraco/vcs/fixtures.py
jaraco/vcs/library.py
jaraco/vcs/reentry.py
jaraco/vcs/subprocess.py
jaraco_vcs-2.4.1.dist-info/LICENSE
jaraco_vcs-2.4.1.dist-info/METADATA
jaraco_vcs-2.4.1.dist-info/WHEEL
jaraco_vcs-2.4.1.dist-info/entry_points.txt
jaraco_vcs-2.4.1.dist-info/top_level.txt
jaraco_vcs-2.4.1.dist-info/RECORD
